position/__init__.py
position/provider/PositionProvider.py
position/provider/__init__.py
position/provider/supplier/PositionSupplier.py
position/provider/supplier/__init__.py
persuader_technology_automata_position-0.1.5.dist-info/LICENSE
persuader_technology_automata_position-0.1.5.dist-info/METADATA
persuader_technology_automata_position-0.1.5.dist-info/WHEEL
persuader_technology_automata_position-0.1.5.dist-info/top_level.txt
persuader_technology_automata_position-0.1.5.dist-info/RECORD
