Metadata-Version: 2.1
Name: persuader-technology-automata-position
Version: 0.1.5
Summary: Automata Position
Author: Persuader Technology
Author-email: software@persuader.technology
License: UNLICENSE
Classifier: Programming Language :: Python :: 3
License-File: LICENSE
Requires-Dist: persuader-technology-automata-core (>=0.6.0)
Requires-Dist: persuader-technology-automata-position-repository (>=0.1.6)
